hn_widget/__init__.py
hn_widget/_version.py
hn_widget/experiment_util.py
hn_widget/widget.py
hn_widget/labextension/package.json
hn_widget/labextension/static/26.572027947c94f6daa27e.js
hn_widget/labextension/static/26.572027947c94f6daa27e.js.LICENSE.txt
hn_widget/labextension/static/261.1486ed629253f83f88df.js
hn_widget/labextension/static/261.4c01f064c6204d8184b9.js
hn_widget/labextension/static/261.4e614468cbcc7e8e766a.js
hn_widget/labextension/static/261.7d4c2f351ab7d99b4e80.js
hn_widget/labextension/static/261.8741bad1fb2ebf7fe531.js
hn_widget/labextension/static/261.bfaf809b3c02b670ac8b.js
hn_widget/labextension/static/309.57e901d09df5a3c595c3.js
hn_widget/labextension/static/309.57e901d09df5a3c595c3.js.LICENSE.txt
hn_widget/labextension/static/486.b11300bd44baf87f14df.js
hn_widget/labextension/static/486.b11300bd44baf87f14df.js.LICENSE.txt
hn_widget/labextension/static/533.9da3c7cb8d1de47b9d7c.js
hn_widget/labextension/static/568.09343949f8057f7cae58.js
hn_widget/labextension/static/568.1d46c846403006044c9c.js
hn_widget/labextension/static/568.31d4a3fda9f18da28116.js
hn_widget/labextension/static/568.4ce93a46ac0c1aec27d9.js
hn_widget/labextension/static/568.4ce93a46ac0c1aec27d9.js.LICENSE.txt
hn_widget/labextension/static/568.9da2fbbd3509d8935f9f.js
hn_widget/labextension/static/568.9da2fbbd3509d8935f9f.js.LICENSE.txt
hn_widget/labextension/static/568.b6763d090c1aa9a30239.js
hn_widget/labextension/static/568.f60291bbdd88ea6573b6.js
hn_widget/labextension/static/613.d15776111b9f51f58e4b.js
hn_widget/labextension/static/835.30da44a4fd9e8627fb9a.js
hn_widget/labextension/static/835.30da44a4fd9e8627fb9a.js.LICENSE.txt
hn_widget/labextension/static/835.52b476cfcced8006bc73.js
hn_widget/labextension/static/835.52b476cfcced8006bc73.js.LICENSE.txt
hn_widget/labextension/static/remoteEntry.048ed1b30111457b1ceb.js
hn_widget/labextension/static/remoteEntry.32d13e41e694afab7c07.js
hn_widget/labextension/static/remoteEntry.44db5ac7a3b55d8f90d9.js
hypernets_jupyter_widget-0.2.3.2.dist-info/METADATA
hypernets_jupyter_widget-0.2.3.2.dist-info/WHEEL
hypernets_jupyter_widget-0.2.3.2.dist-info/top_level.txt
hypernets_jupyter_widget-0.2.3.2.dist-info/RECORD
