Metadata-Version: 2.1
Name: hypernets-jupyter-widget
Version: 0.2.3.2
Summary: Jupyter widgets for hyperntes
Home-page: https://github.com/DataCanvas/hn_widget
Author: wuhf
Author-email: wuhf@zetyun.com
License: UNKNOWN
Keywords: ipython,jupyter,widgets
Platform: UNKNOWN
Classifier: Development Status :: 4 - Beta
Classifier: Framework :: IPython
Classifier: Intended Audience :: Developers
Classifier: Intended Audience :: Science/Research
Classifier: Topic :: Multimedia :: Graphics
Classifier: Programming Language :: Python :: 3.6
Classifier: Programming Language :: Python :: 3.7
Classifier: Programming Language :: Python :: 3.8
Classifier: Programming Language :: Python :: 3.9
Requires-Dist: ipywidgets (>=7.6.0)
Requires-Dist: numpy
Requires-Dist: pandas
